tshistory_client/__init__.py
tshistory_client/api.py
tshistory_client-0.8.0.dist-info/METADATA
tshistory_client-0.8.0.dist-info/WHEEL
tshistory_client-0.8.0.dist-info/top_level.txt
tshistory_client-0.8.0.dist-info/RECORD
