Metadata-Version: 2.1
Name: tshistory-client
Version: 0.8.0
Summary: Timeseries histories python client (server side: tshistory_rest)
Home-page: https://hg.sr.ht/~pythonian/tshistory_client
Author: Pythonian
Author-email: aurelien.campeas@pythonian.fr
License: UNKNOWN
Platform: UNKNOWN
Classifier: Development Status :: 4 - Beta
Classifier: Intended Audience :: Developers
Classifier: License :: OSI Approved :: GNU Lesser General Public License v3 (LGPLv3)
Classifier: Operating System :: OS Independent
Classifier: Programming Language :: Python :: 3
Classifier: Topic :: Database
Classifier: Topic :: Scientific/Engineering
Classifier: Topic :: Software Development :: Version Control
Requires-Dist: requests
Requires-Dist: pandas
Requires-Dist: pytest-sa-pg
